setup.py
TracPwAuth.egg-info/PKG-INFO
TracPwAuth.egg-info/SOURCES.txt
TracPwAuth.egg-info/dependency_links.txt
TracPwAuth.egg-info/entry_points.txt
TracPwAuth.egg-info/requires.txt
TracPwAuth.egg-info/top_level.txt
pwauth/__init__.py
pwauth/_subprocess.py
pwauth/store.py
