Metadata-Version: 1.0
Name: TracPwAuth
Version: 1.0
Summary: An AccountManager password store that uses pwauth to check against the system password databse.
Home-page: http://trac-hacks.org/wiki/PwAuthPlugin
Author: Noah Kantrowitz
Author-email: coderanger@yahoo.com
License: BSD
Keywords: trac plugin accountmanager
Platform: UNKNOWN
Classifier: Framework :: Trac
